pymux/__init__.py
pymux/__main__.py
pymux/arrangement.py
pymux/client.py
pymux/darwin.py
pymux/enums.py
pymux/filters.py
pymux/format.py
pymux/key_bindings.py
pymux/key_mappings.py
pymux/layout.py
pymux/log.py
pymux/main.py
pymux/options.py
pymux/process.py
pymux/rc.py
pymux/screen.py
pymux/server.py
pymux/stream.py
pymux/style.py
pymux/utils.py
pymux/commands/__init__.py
pymux/commands/aliases.py
pymux/commands/commands.py
pymux/commands/completer.py
pymux/commands/utils.py
pymux/entry_points/__init__.py
pymux/entry_points/run_pymux.py
pymux-0.14.dist-info/DESCRIPTION.rst
pymux-0.14.dist-info/METADATA
pymux-0.14.dist-info/RECORD
pymux-0.14.dist-info/WHEEL
pymux-0.14.dist-info/entry_points.txt
pymux-0.14.dist-info/metadata.json
pymux-0.14.dist-info/top_level.txt
