Metadata-Version: 2.0
Name: pymux
Version: 0.14
Summary: Pure Python terminal multiplexer.
Home-page: https://github.com/jonathanslenders/
Author: Jonathan Slenders
Author-email: UNKNOWN
License: LICENSE
Platform: UNKNOWN
Requires-Dist: docopt (>=0.6.2)
Requires-Dist: prompt-toolkit (<1.1.0,>=1.0.8)
Requires-Dist: pyte (<0.6.0,>=0.5.1)
Requires-Dist: six (>=1.9.0)
